yabai_navigation_utilities/__init__.py
yabai_navigation_utilities/__main__.py
yabai_navigation_utilities/cli.py
yabai_navigation_utilities/config.py
yabai_navigation_utilities-0.0.14.dist-info/METADATA
yabai_navigation_utilities-0.0.14.dist-info/WHEEL
yabai_navigation_utilities-0.0.14.dist-info/entry_points.txt
yabai_navigation_utilities-0.0.14.dist-info/top_level.txt
yabai_navigation_utilities-0.0.14.dist-info/RECORD
