Metadata-Version: 2.1
Name: yabai-navigation-utilities
Version: 0.0.14
Summary: Collection of scripts to make navigating Yabai easier.
Author: Sendhil Panchadsaram
License: MIT
Project-URL: GitHub, https://github.com/sendhil/yabai-navigation-utilities
Requires-Dist: click (==8.1.3)
